csdt/__init__.py
csdt/csdt.py
csdt-1.0.9.dist-info/LICENSE
csdt-1.0.9.dist-info/METADATA
csdt-1.0.9.dist-info/WHEEL
csdt-1.0.9.dist-info/top_level.txt
csdt-1.0.9.dist-info/RECORD
