Metadata-Version: 2.1
Name: csdt
Version: 1.0.9
Summary: Custom Split Decision Tree
Home-page: https://github.com/sibirbil/CSDT.git
Author: Çağla Mıdıklı, İlker Birbil, Doğanay Özese
Author-email: midiklicagla@gmail.com
License: MIT
Classifier: Programming Language :: Python :: 3
Classifier: Programming Language :: Python :: 3.8
Classifier: Programming Language :: Python :: 3.9
Classifier: Programming Language :: Python :: 3.10
Classifier: Programming Language :: Python :: 3.11
Classifier: License :: OSI Approved :: MIT License
Classifier: Operating System :: OS Independent
Classifier: Intended Audience :: Developers
Classifier: Intended Audience :: Education
Classifier: Topic :: Scientific/Engineering :: Artificial Intelligence
Classifier: Topic :: Software Development :: Libraries :: Python Modules
Requires-Python: >=3.6, <3.12
License-File: LICENSE
Requires-Dist: matplotlib==3.8.1
Requires-Dist: numpy==1.26.0
Requires-Dist: pandas==2.1.3
Requires-Dist: graphviz
